{
  "default": {
    "design": {
      "neckline":   {"type": "nek", "id": "009", "fabric": "003"}
      , "skirt":    {"type": "skt", "id": "030", "fabric": "003", "trim": ""}
      , "sleeves":  {"type": "slv", "id": "001", "fabric": "003"}
    }
    , "belt": {
      "belt":     {"type": "blt", "id": "004", "fabric": "120"}
    }
    , "extras": {
      "peplum": {"type": "ext", "id": "000", "fabric": "003"}
      , "rosetta": {"type": "ext", "id": "000", "fabric": "011"}
    }
  }
  , "fabricSets": [ {"setId": "s-vc"}, {"setId": "x-fl"}, {"setId": "x-sq"}]
  , "trimFabricSets": [{"setId": "s-tr"}]
  , "sizes": [10,12,14,16,18]
  , "options": [
  {
    "option_name": "design"
    , "active": "true"
    , "default": "in"
    , "label": "Customise Dress"
    , "parts": [
    {
      "part_name": "neckline"
      , "type": "nek"
      , "active": "true"
      , "label": "Neckline"
      , "fabricSets": [{"setId": "s-vc"}, {"setId": "x-fl"}]
      , "values": [
        {"id": "010"}
      , {"id": "009"}
    ]
      , "trim": true
      , "trimFabricSets": [ {"setId": "s-tr"}]
    }
    ,{
      "part_name": "sleeves"
      , "type": "slv"
      , "label": "Sleeves"
      , "fabricSets": [ {"setId": "s-vc"}, {"setId": "x-fl"}, {"setId": "x-sq"}]
      , "values": [
        {"id": "000"},
        {"id": "001"},
        {"id": "006"},
        {"id": "007"}
      ]
      , "trim": false
    }
    ,{
      "part_name": "skirt"
      , "type": "skt"
      , "label": "Skirt"
      , "fabricSets": [{"setId": "s-vc"}, {"setId": "x-fl"}]
      , "values": [
        {"id": "031"}
        , {"id": "032"}
        , {"id": "034"}
      ]
      , "trim": false
      , "trimFabricSets": [{"setId": "s-tr"}]
    }
  ]
  }
  , {
    "option_name": "extras"
    , "label": "Extras"
    , "parts": [
      {
        "part_name": "belt"
        , "type": "blt"
        , "active": "true"
        , "label": "Belt"
        , "fabricSets": [ {"setId": "x-pt"}]
        , "values": [
        {"id": "002"}
        , {"id": "003"}
        , {"id": "004"}
      ]
      }
      , {
        "part_name": "rosetta"
        , "type": "ext"
        , "label": "Rosetta"
        , "fabricSets": [ {"setId": "s-vc"}, {"setId": "x-fl"}]
        , "values": [
          {"id": "000"}
          , {"id": "003"}
        ]
      }
    ]}

]
}
